[
  {
    "referrer": "github.com",
    "count": 215,
    "uniques": 52
  },
  {
    "referrer": "Google",
    "count": 84,
    "uniques": 26
  },
  {
    "referrer": "slimbootloader.github.io",
    "count": 62,
    "uniques": 12
  },
  {
    "referrer": "intel.com",
    "count": 21,
    "uniques": 11
  },
  {
    "referrer": "DuckDuckGo",
    "count": 9,
    "uniques": 3
  },
  {
    "referrer": "groups.io",
    "count": 7,
    "uniques": 7
  },
  {
    "referrer": "Bing",
    "count": 7,
    "uniques": 6
  },
  {
    "referrer": "statics.teams.cdn.office.net",
    "count": 4,
    "uniques": 3
  },
  {
    "referrer": "yandex.ru",
    "count": 4,
    "uniques": 2
  },
  {
    "referrer": "basicinputoutput.com",
    "count": 3,
    "uniques": 3
  }
]
